[
  { "section": "Verbs", "kanji": "包みます", "hiragana": "つつみます", "meaning": "wrap", "emoji": "🎁" },
  { "section": "Verbs", "kanji": "沸かします", "hiragana": "わかします", "meaning": "boil", "emoji": "🫖🔥" },
  { "section": "Verbs", "kanji": "混ぜます", "hiragana": "まぜます", "meaning": "mix", "emoji": "🥄🌀" },
  { "section": "Verbs", "kanji": "計算します", "hiragana": "けいさんします", "meaning": "calculate", "emoji": "🧮" },
  { "section": "Adjectives", "kanji": "厚い", "hiragana": "あつい", "meaning": "thick", "emoji": "📘" },
  { "section": "Adjectives", "kanji": "薄い", "hiragana": "うすい", "meaning": "thin", "emoji": "📄" },
  { "section": "Nouns", "kanji": "弁護士", "hiragana": "べんごし", "meaning": "lawyer, attorney", "emoji": "⚖️" },
  { "section": "Nouns", "kanji": "音楽家", "hiragana": "おんがくか", "meaning": "musician", "emoji": "🎻" },
  { "section": "Nouns", "kanji": "子どもたち", "hiragana": "こどもたち", "meaning": "children", "emoji": "🧒" },
  { "section": "Nouns", "kanji": "二人", "hiragana": "ふたり", "meaning": "couple", "emoji": "👫" },
  { "section": "Nouns", "kanji": "教育", "hiragana": "きょういく", "meaning": "education", "emoji": "🎓" },
  { "section": "Nouns", "kanji": "歴史", "hiragana": "れきし", "meaning": "history", "emoji": "📜" },
  { "section": "Nouns", "kanji": "文化", "hiragana": "ぶんか", "meaning": "culture", "emoji": "🎎" },
  { "section": "Nouns", "kanji": "社会", "hiragana": "しゃかい", "meaning": "society", "emoji": "🏙️" },
  { "section": "Nouns", "kanji": "法律", "hiragana": "ほうりつ", "meaning": "law", "emoji": "⚖️📜" },
  { "section": "Nouns", "kanji": "戦争", "hiragana": "せんそう", "meaning": "war", "emoji": "⚔️" },
  { "section": "Nouns", "kanji": "平和", "hiragana": "へいわ", "meaning": "peace", "emoji": "🕊️" },
  { "section": "Nouns", "kanji": "目的", "hiragana": "もくてき", "meaning": "purpose", "emoji": "🎯" },
  { "section": "Nouns", "kanji": "安全", "hiragana": "あんぜん", "meaning": "safety", "emoji": "🛡️" },
  { "section": "Nouns", "kanji": "論文", "hiragana": "ろんぶん", "meaning": "thesis, academic paper", "emoji": "📝" },
  { "section": "Nouns", "kanji": "関係", "hiragana": "かんけい", "meaning": "relation, connection", "emoji": "🔗" },
  { "section": "Nouns", "kanji": "ミキサー", "hiragana": "ミキサー", "meaning": "mixer, blender", "emoji": "🌪️" },
  { "section": "Nouns", "kanji": "やかん", "hiragana": "やかん", "meaning": "kettle", "emoji": "🫖" },
  { "section": "Nouns", "kanji": "栓抜き", "hiragana": "せんぬき", "meaning": "cap opener", "emoji": "🍾" },
  { "section": "Nouns", "kanji": "缶切り", "hiragana": "かんきり", "meaning": "can opener", "emoji": "🥫" },
  { "section": "Nouns", "kanji": "缶詰", "hiragana": "かんづめ", "meaning": "canned food, tinned food", "emoji": "🥫" },
  { "section": "Nouns", "kanji": "ふろしき", "hiragana": "ふろしき", "meaning": "wrapping cloth used to carry things", "emoji": "🧣" },
  { "section": "Nouns", "kanji": "そろばん", "hiragana": "そろばん", "meaning": "abacus", "emoji": "🧮" },
  { "section": "Nouns", "kanji": "体温計", "hiragana": "たいおんけい", "meaning": "(clinical) thermometer", "emoji": "🌡️" },
  { "section": "Nouns", "kanji": "材料", "hiragana": "ざいりょう", "meaning": "material, ingredient", "emoji": "🥣" },
  { "section": "Nouns", "kanji": "石", "hiragana": "いし", "meaning": "stone", "emoji": "🪨" },
  { "section": "Nouns", "kanji": "ピラミッド", "hiragana": "ピラミッド", "meaning": "pyramid", "emoji": "🔺" },
  { "section": "Nouns", "kanji": "データ", "hiragana": "データ", "meaning": "data", "emoji": "💾" },
  { "section": "Nouns", "kanji": "ファイル", "hiragana": "ファイル", "meaning": "file", "emoji": "📁" },
  { "section": "Other", "kanji": "ある ~", "hiragana": "ある ~", "meaning": "a certain ~, one ~", "emoji": "🔍" },
  { "section": "Other", "kanji": "一生懸命", "hiragana": "いっしょうけんめい", "meaning": "with all one's effort", "emoji": "💪" },
  { "section": "Other", "kanji": "なぜ", "hiragana": "なぜ", "meaning": "why", "emoji": "❓" },
  { "section": "Proper Nouns", "kanji": "国連", "hiragana": "こくれん", "meaning": "United Nations", "emoji": "🇺🇳" },
  { "section": "Proper Nouns", "kanji": "エリーゼのために", "hiragana": "エリーゼのために", "meaning": "Für Elise", "emoji": "🎹" },
  { "section": "Proper Nouns", "kanji": "ベートーベン", "hiragana": "ベートーベン", "meaning": "Ludwig van Beethoven, German composer", "emoji": "👨‍🦳" },
  { "section": "Proper Nouns", "kanji": "ポーランド", "hiragana": "ポーランド", "meaning": "Poland", "emoji": "🇵🇱" },
  { "section": "Conversation", "kanji": "ローン", "hiragana": "ローン", "meaning": "loan", "emoji": "💳" },
  { "section": "Conversation", "kanji": "セット", "hiragana": "セット", "meaning": "set", "emoji": "📦" },
  { "section": "Conversation", "kanji": "あと", "hiragana": "あと", "meaning": "the amount left unused, the rest", "emoji": "⏳" },
  { "section": "Reading", "kanji": "カップラーメン", "hiragana": "カップラーメン", "meaning": "instant Chinese noodles (disposable container)", "emoji": "🍜" },
  { "section": "Reading", "kanji": "インスタントラーメン", "hiragana": "インスタントラーメン", "meaning": "instant Chinese noodles", "emoji": "🍜" },
  { "section": "Reading", "kanji": "なべ", "hiragana": "なべ", "meaning": "pan, pot", "emoji": "🍲" },
  { "section": "Reading", "kanji": "どんぶり", "hiragana": "どんぶり", "meaning": "ceramic bowl", "emoji": "🥣" },
  { "section": "Reading", "kanji": "食品", "hiragana": "しょくひん", "meaning": "food", "emoji": "🍎" },
  { "section": "Reading", "kanji": "調査", "hiragana": "ちょうさ", "meaning": "investigation, survey", "emoji": "🔎" },
  { "section": "Reading", "kanji": "カップ", "hiragana": "カップ", "meaning": "cup", "emoji": "🥤" },
  { "section": "Reading", "kanji": "また", "hiragana": "また", "meaning": "and", "emoji": "➕" },
  { "section": "Reading", "kanji": "~の代わりに", "hiragana": "~のかわりに", "meaning": "in place of ~, instead of ~", "emoji": "🔄" },
  { "section": "Reading", "kanji": "どこでも", "hiragana": "どこでも", "meaning": "in any place", "emoji": "🌏" },
  { "section": "Reading", "kanji": "今では", "hiragana": "いまでは", "meaning": "now", "emoji": "⏳" }
]